iqual/__init__.py
iqual/crossval.py
iqual/estimation.py
iqual/evaluation.py
iqual/feature_transform.py
iqual/iqualnlp.py
iqual/preprocessing.py
iqual/tests.py
iqual/utils.py
iqual/vectorizers.py
iQual-0.1.2.dist-info/LICENSE.md
iQual-0.1.2.dist-info/METADATA
iQual-0.1.2.dist-info/WHEEL
iQual-0.1.2.dist-info/top_level.txt
iQual-0.1.2.dist-info/RECORD
