Metadata-Version: 2.1
Name: iQual
Version: 0.1.2
Summary: iQual is a package that leverages natural language processing to scale up interpretative qualitative analysis. It also provides methods to assess the bias, interpretability and efficiency of the machine-enhanced codes.
Home-page: https://github.com/worldbank/iQual
Author: Aditya Karan Chhabra
Author-email: aditya0chhabra@gmail.com
Maintainer: Aditya Karan Chhabra
Maintainer-email: aditya0chhabra@gmail.com
License: MIT
Keywords: nlp natural-language-processing qualitative-analysis human-coding qualitative-research
Classifier: Development Status :: 3 - Alpha
Classifier: Intended Audience :: Science/Research
Classifier: Topic :: Sociology
Classifier: Topic :: Utilities
Classifier: Topic :: Text Processing :: Linguistic
Classifier: Topic :: Scientific/Engineering :: Information Analysis
Classifier: License :: OSI Approved :: MIT License
Classifier: Programming Language :: Python :: 3
Classifier: Programming Language :: Python :: 3.7
Classifier: Programming Language :: Python :: 3.8
Classifier: Programming Language :: Python :: 3.9
Classifier: Programming Language :: Python :: 3.10
Requires-Python: >=3.7
License-File: LICENSE.md
Requires-Dist: scikit-learn (>=1.1.0)
Requires-Dist: sentence-transformers
Requires-Dist: umap-learn
Requires-Dist: pandas
Requires-Dist: numpy
Requires-Dist: scipy
Requires-Dist: simplejson
Requires-Dist: statsmodels
Requires-Dist: spacy
Requires-Dist: matplotlib
Requires-Dist: seaborn
